scrapethedocs/__init__.py
scrapethedocs/_helpers.py
scrapethedocs/_link_extraction.py
scrapethedocs/_text_extraction.py
scrapethedocs-0.1.0.dist-info/LICENSE
scrapethedocs-0.1.0.dist-info/WHEEL
scrapethedocs-0.1.0.dist-info/METADATA
scrapethedocs-0.1.0.dist-info/RECORD
